fcloud/__init__.py
fcloud/test.py
fcloud/fauth/__init__.py
fcloud/fmap/__init__.py
fcloud/fmap/data.py
fcloud/fmap/fmap.py
fcloud/friday/__init__.py
fcloud/friday/datastructures.py
fcloud/friday/dictionary.py
fcloud/friday/friday.py
fcloud/friday/parsers.py
fcloud/friday/utils.py
fcloud-0.1.2.dist-info/METADATA
fcloud-0.1.2.dist-info/WHEEL
fcloud-0.1.2.dist-info/top_level.txt
fcloud-0.1.2.dist-info/RECORD
