Metadata-Version: 2.1
Name: fcloud
Version: 0.1.2
Summary: [DEV]
Home-page: https://github.com/Nandan-unni
Author: Nandanunni A S
Author-email: asnqln@gmail.com
License: MIT
Platform: UNKNOWN
Classifier: License :: OSI Approved :: MIT License
Classifier: Programming Language :: Python :: 3
Classifier: Programming Language :: Python :: 3.7
Classifier: Operating System :: OS Independent
Requires-Python: >=3.6
